README.md
setup.cfg
setup.py
chance_mock_logger.egg-info/PKG-INFO
chance_mock_logger.egg-info/SOURCES.txt
chance_mock_logger.egg-info/dependency_links.txt
chance_mock_logger.egg-info/not-zip-safe
chance_mock_logger.egg-info/requires.txt
chance_mock_logger.egg-info/top_level.txt
mock_logger/__init__.py
mock_logger/handler.py