Metadata-Version: 1.0
Name: chance-mock-logger
Version: 0.0.2
Summary: The mock logging handler for chancefocus
Home-page: https://git.chancefocus.com/transaction/common/chance-mock-logger.git
Author: Jimin Huang
Author-email: huangjimin@whu.edu.cn
License: MIT
Platform: UNKNOWN
